quickstatandeda/.DS_Store
quickstatandeda/__init__.py
quickstatandeda/autoregression.py
quickstatandeda/dataframepreparation.py
quickstatandeda/htmlpreparation.py
quickstatandeda/quickstatandeda.py
quickstatandeda-0.1.11.dist-info/LICENSE
quickstatandeda-0.1.11.dist-info/METADATA
quickstatandeda-0.1.11.dist-info/WHEEL
quickstatandeda-0.1.11.dist-info/top_level.txt
quickstatandeda-0.1.11.dist-info/RECORD
