Metadata-Version: 2.1
Name: quickstatandeda
Version: 0.1.11
Summary: The quickstatandeda package aims to generate visuals and an main html file for any Python Pandas DataFrame
Author-email: Kaichong Zhang <kzhang.matt@gmail.com>
Classifier: Programming Language :: Python :: 3
Classifier: License :: OSI Approved :: MIT License
Classifier: Topic :: Scientific/Engineering :: Visualization
Requires-Python: >3.8
License-File: LICENSE
